odoo/addons/ddmrp_coverage_days/README.rst
odoo/addons/ddmrp_coverage_days/__init__.py
odoo/addons/ddmrp_coverage_days/__manifest__.py
odoo/addons/ddmrp_coverage_days/i18n/ddmrp_coverage_days.pot
odoo/addons/ddmrp_coverage_days/i18n/es.po
odoo/addons/ddmrp_coverage_days/i18n/it.po
odoo/addons/ddmrp_coverage_days/i18n/pt_BR.po
odoo/addons/ddmrp_coverage_days/models/__init__.py
odoo/addons/ddmrp_coverage_days/models/stock_buffer.py
odoo/addons/ddmrp_coverage_days/readme/CONTRIBUTORS.md
odoo/addons/ddmrp_coverage_days/readme/DESCRIPTION.md
odoo/addons/ddmrp_coverage_days/readme/HISTORY.md
odoo/addons/ddmrp_coverage_days/static/description/icon.png
odoo/addons/ddmrp_coverage_days/static/description/index.html
odoo/addons/ddmrp_coverage_days/tests/__init__.py
odoo/addons/ddmrp_coverage_days/tests/test_ddmrp_coverage_days.py
odoo/addons/ddmrp_coverage_days/views/stock_buffer_views.xml
odoo_addon_ddmrp_coverage_days-18.0.1.0.0.2.dist-info/METADATA
odoo_addon_ddmrp_coverage_days-18.0.1.0.0.2.dist-info/WHEEL
odoo_addon_ddmrp_coverage_days-18.0.1.0.0.2.dist-info/top_level.txt
odoo_addon_ddmrp_coverage_days-18.0.1.0.0.2.dist-info/RECORD
